pypeman/__init__.py
pypeman/channels.py
pypeman/commands.py
pypeman/conf.py
pypeman/debug.py
pypeman/default_settings.py
pypeman/endpoints.py
pypeman/errors.py
pypeman/events.py
pypeman/exceptions.py
pypeman/graph.py
pypeman/map_item.py
pypeman/message.py
pypeman/msgstore.py
pypeman/nodes.py
pypeman/persistence.py
pypeman/pjt_templates.py
pypeman/plugin_mgr.py
pypeman/remoteadmin.py
pypeman/retry.py
pypeman/test.py
pypeman/tool_commands.py
pypeman/contrib/__init__.py
pypeman/contrib/csv.py
pypeman/contrib/ctx.py
pypeman/contrib/ftp.py
pypeman/contrib/hl7.py
pypeman/contrib/http.py
pypeman/contrib/time.py
pypeman/contrib/xml.py
pypeman/helpers/__init__.py
pypeman/helpers/aio_compat.py
pypeman/helpers/cli.py
pypeman/helpers/itertools.py
pypeman/helpers/lazyload.py
pypeman/helpers/logging.py
pypeman/helpers/reloader.py
pypeman/helpers/sleeper.py
pypeman/helpers/tempfile.py
pypeman/plugins/__init__.py
pypeman/plugins/base.py
pypeman/plugins/remoteadmin/__init__.py
pypeman/plugins/remoteadmin/plugin.py
pypeman/plugins/remoteadmin/urls.py
pypeman/plugins/remoteadmin/views.py
pypeman/tests/__init__.py
pypeman/tests/common.py
pypeman/tests/pytest_helpers.py
pypeman/tests/test_channel.py
pypeman/tests/test_ctx_nodes.py
pypeman/tests/test_debug.py
pypeman/tests/test_graph.py
pypeman/tests/test_import_mods.py
pypeman/tests/test_imports.py
pypeman/tests/test_message.py
pypeman/tests/test_msgstore.py
pypeman/tests/test_nodes.py
pypeman/tests/test_remoteadmin.py
pypeman/tests/test_retrystore.py
pypeman/tests/test_settings.py
pypeman/tests/test_testing.py
pypeman/tests/tests_bin.py
pypeman/tests/data/csv_test_data.csv
pypeman/tests/data/hl7_test_data.HL7
pypeman/tests/data/new_meta.meta
pypeman/tests/data/old_meta.meta
pypeman/tests/data/testfile.ok
pypeman/tests/data/testfile.txt
pypeman/tests/settings/__init__.py
pypeman/tests/settings/test_setting_1.py
pypeman/tests/settings/test_settings_default.py
pypeman/tests/settings/test_settings_persistence.py
pypeman-0.6.0.dist-info/LICENSE
pypeman-0.6.0.dist-info/METADATA
pypeman-0.6.0.dist-info/WHEEL
pypeman-0.6.0.dist-info/entry_points.txt
pypeman-0.6.0.dist-info/top_level.txt
pypeman-0.6.0.dist-info/RECORD
