Metadata-Version: 2.1
Name: pypeman
Version: 0.6.0
Summary: Minimalistic but pragmatic ESB / ETL / EAI in Python
Home-page: https://github.com/mhcomm/pypeman
Author: Jeremie Pardou
Author-email: jeremie@jeremiez.net
License: Apache Software License
Keywords: esb etl eai pipeline data processing asyncio http ftp hl7
Classifier: Development Status :: 4 - Beta
Classifier: License :: OSI Approved :: Apache Software License
Classifier: Programming Language :: Python :: 3.7
Classifier: Programming Language :: Python :: 3.8
Classifier: Programming Language :: Python :: 3.9
Classifier: Programming Language :: Python :: 3.10
Classifier: Programming Language :: Python :: 3 :: Only
Classifier: Intended Audience :: Developers
Classifier: Intended Audience :: Information Technology
Classifier: Intended Audience :: Healthcare Industry
Classifier: Operating System :: POSIX :: Linux
Classifier: Topic :: Database
Classifier: Topic :: Internet
Classifier: Topic :: Internet :: File Transfer Protocol (FTP)
Classifier: Programming Language :: Python
License-File: LICENSE
Requires-Dist: click
Requires-Dist: daemonlite
Requires-Dist: python-dateutil
Requires-Dist: websockets<14
Requires-Dist: aiohttp
Requires-Dist: jsonrpcclient
Requires-Dist: jsonrpcserver<5
Requires-Dist: sqlitedict
Requires-Dist: requests
Provides-Extra: all
Requires-Dist: hl7; extra == "all"
Requires-Dist: xmltodict; extra == "all"
Requires-Dist: aiocron; extra == "all"
Provides-Extra: hl7
Requires-Dist: hl7; extra == "hl7"
Provides-Extra: time
Requires-Dist: aiocron; extra == "time"
Provides-Extra: xml
Requires-Dist: xmltodict; extra == "xml"
